{
  "containerDefinitions": [
    {
      "name": "unicorn-container",
      "image": "486463126616.dkr.ecr.ap-northeast-1.amazonaws.com/sample-image:unicorn-latest",
      "cpu": 333,
      "memoryReservation": 600,
      "portMappings": [
        {
          "containerPort": 3000,
          "hostPort": 3000,
          "protocol": "tcp"
        }
      ],
      "essential": true,
      "command": [
        "unicorn",
        "-c",
        "/app/config/unicorn.rb"
      ],
      "environment": [
        {
          "name": "RAILS_ENV",
          "value": "production"
        },
        {
          "name": "RACK_ENV",
          "value": "production"
        }
      ],
      "mountPoints": [
        {
          "sourceVolume": "sockets-share",
          "containerPath": "/app/sockets",
          "readOnly": false
        }
      ],
      "volumesFrom": [],
      "logConfiguration": {
        "logDriver": "awslogs",
        "options": {
          "awslogs-group": "sample-service",
          "awslogs-region": "ap-northeast-1",
          "awslogs-stream-prefix": "unicorn"
        }
      }
    },
    {
      "name": "nginx-container",
      "image": "486463126616.dkr.ecr.ap-northeast-1.amazonaws.com/sample-image:nginx-latest",
      "cpu": 333,
      "memoryReservation": 600,
      "portMappings": [
        {
          "containerPort": 80,
          "hostPort": 0,
          "protocol": "tcp"
        }
      ],
      "essential": true,
      "command": [
        "nginx",
        "-g",
        "daemon off;",
        "-c",
        "/etc/nginx/nginx.conf"
      ],
      "environment": [],
      "mountPoints": [
        {
          "sourceVolume": "sockets-share",
          "containerPath": "/app/sockets",
          "readOnly": false
        }
      ],
      "volumesFrom": [],
      "logConfiguration": {
        "logDriver": "awslogs",
        "options": {
          "awslogs-group": "sample-service",
          "awslogs-region": "ap-northeast-1",
          "awslogs-stream-prefix": "nginx"
        }
      }
    }
  ],
  "volumes": [
    {
      "name": "sockets-share"
    }
  ]
}
